{
    "transactions": [
        {
            "recipientId": "K7NaofCDp4pSDR5hXRjuGVeyaVeqb9qs2B",
            "amount": 453700371
        },
        {
            "recipientId": "KMLFFymTTZtryGZHsCMD5GYuBjSzEZW8wB",
            "amount": 181214115874
        },
        {
            "recipientId": "KFjkayaDf4KnSgXHFQbTaHZwsEoo1CMNPi",
            "amount": 25748511676
        },
        {
            "recipientId": "KKG8zY6Ya8QJkZXykVoRpEG5bui3noAEZe",
            "amount": 260884008749
        },
        {
            "recipientId": "K8r6RtjoBKqfLF4oWQBdDf33DsD83Y3syw",
            "amount": 15350006241
        },
        {
            "recipientId": "KBTqDz2Uz3CbgkBtQ1eXCgtq8ANdWTmCiJ",
            "amount": 80816349176
        },
        {
            "recipientId": "KLBKDKjqzbP43Ekfz7PykBQMXkhwgDZLjA",
            "amount": 31513307909
        }
    ],
    "transactionsPending": [],
    "donations": [],
    "donationsPercentage": []
}